updownio/__init__.py
updownio/service.py
updownio/services/__init__.py
updownio/services/checks.py
updownio/services/nodes.py
updownio/services/recipients.py
updownio/services/status_pages.py
updownio-0.0.10.dist-info/LICENSE
updownio-0.0.10.dist-info/METADATA
updownio-0.0.10.dist-info/WHEEL
updownio-0.0.10.dist-info/top_level.txt
updownio-0.0.10.dist-info/RECORD
