Metadata-Version: 2.1
Name: updownio
Version: 0.0.10
Summary: Client library for updown.io API.
Home-page: https://github.com/decryptus/updownio
Author: Adrien Delle Cave
Author-email: pypi@doowan.net
License: License GPL-3
Platform: UNKNOWN
Classifier: License :: OSI Approved :: GNU General Public License v3 (GPLv3)
Classifier: Natural Language :: English
Classifier: Operating System :: Unix
Classifier: Programming Language :: Python
Classifier: Programming Language :: Python :: 2
Classifier: Programming Language :: Python :: 2.7
Classifier: Programming Language :: Python :: 3
Classifier: Programming Language :: Python :: 3.5
Classifier: Programming Language :: Python :: 3.6
Classifier: Programming Language :: Python :: 3.7
Classifier: Programming Language :: Python :: 3.9
Classifier: Topic :: System :: Monitoring
Classifier: Topic :: Utilities
Requires-Python: >=2.7, !=3.0.*, !=3.1.*, !=3.2.*, !=3.3.*, !=3.4.*
Requires-Dist: requests (>=2.21.0)
Requires-Dist: sonicprobe (>=0.3.51)
